zorp/__init__.py
zorp/assets.py
zorp/const.py
zorp/exceptions.py
zorp/lookups.py
zorp/parser_utils.py
zorp/parsers.py
zorp/readers.py
zorp/sniffers.py
zorp/bin/__init__.py
zorp/bin/zorp_convert.py
zorp/loaders/__init__.py
zorp/loaders/make_rsid_lookup.py
zorp/loaders/alternatives/__init__.py
zorp/loaders/alternatives/snp_to_rsid_tabix.py
zorp-0.3.8.dist-info/LICENSE
zorp-0.3.8.dist-info/METADATA
zorp-0.3.8.dist-info/WHEEL
zorp-0.3.8.dist-info/entry_points.txt
zorp-0.3.8.dist-info/top_level.txt
zorp-0.3.8.dist-info/RECORD
