Metadata-Version: 2.1
Name: zorp
Version: 0.3.8
Summary: ZORP: A helpful GWAS parser
Home-page: https://github.com/abought/zorp
Author: Andy Boughton
Author-email: abought@umich.edu
Project-URL: Bug Reports, https://github.com/abought/zorp/issues
Project-URL: Source, https://github.com/abought/zorp/
Keywords: sample setuptools development
Classifier: Development Status :: 4 - Beta
Classifier: Intended Audience :: Developers
Classifier: License :: OSI Approved :: MIT License
Classifier: Programming Language :: Python :: 3.5
Classifier: Programming Language :: Python :: 3.6
Classifier: Programming Language :: Python :: 3.7
Requires-Python: >=3.5
License-File: LICENSE
Requires-Dist: pysam
Requires-Dist: filefetcher
Provides-Extra: lookups
Requires-Dist: lmdb ; extra == 'lookups'
Requires-Dist: msgpack (==1.0.0) ; extra == 'lookups'
Provides-Extra: perf
Requires-Dist: fastnumbers (==3.2.1) ; extra == 'perf'
Provides-Extra: test
Requires-Dist: coverage ; extra == 'test'
Requires-Dist: pytest ; extra == 'test'
Requires-Dist: pytest-flake8 ; extra == 'test'
Requires-Dist: pytest-mypy ; extra == 'test'
